[
  {
    "name": "file",
    "species" : "<img src = 'https://demo.lytrod.com/wp-content/uploads/2020/01/computer-2-1-150x150-1.png'>",
    "foods": {
      "likes": ["tuna", "catnip"],
      "dislikes": ["ham", "zucchini"]
    }
  },
  {
    "name": "Barky",
    "species" : "dog",
    "foods": {
      "likes": ["bones", "carrots"],
      "dislikes": ["tuna"]
    }
  },
  {
    "name": "Purrpaws",
    "species" : "cat",
    "foods": {
      "likes": ["mice"],
      "dislikes": ["cookies"]
    }
  }
]
